hypernova/__init__.py
hypernova/plugins/__init__.py
hypernova/plugins/dev_mode.py
hypernova-0.0.3.dist-info/DESCRIPTION.rst
hypernova-0.0.3.dist-info/METADATA
hypernova-0.0.3.dist-info/RECORD
hypernova-0.0.3.dist-info/WHEEL
hypernova-0.0.3.dist-info/metadata.json
hypernova-0.0.3.dist-info/top_level.txt
