Metadata-Version: 2.0
Name: hypernova
Version: 0.0.3
Summary: Python client for Hypernova, https://github.com/airbnb/hypernova
Home-page: https://github.com/ornj/hypernova-python
Author: Stephen Hurwitz
Author-email: ornj@stevehurwitz.com
License: MIT License
Keywords: hypernova react javascript client
Platform: UNKNOWN
Classifier: Development Status :: 3 - Alpha
Classifier: Intended Audience :: Developers
Classifier: License :: OSI Approved :: MIT License
Classifier: Natural Language :: English
Classifier: Programming Language :: Python
Requires-Dist: requests
Requires-Dist: six
